{"is_source_file": true, "format": "TypeScript (TSX)", "description": "This file defines a React component 'HelloWorld' for use with the Remotion library, including styling, animations, and schema validation for props. It imports other components such as Logo, Title, Subtitle and uses external libraries like 'remotion' and 'zod'.", "external_files": ["./HelloWorld/Logo", "./HelloWorld/Subtitle", "./HelloWorld/Title"], "external_methods": ["spring", "interpolate", "useCurrentFrame", "useVideoConfig"], "published": ["HelloWorld", "myCompSchema"], "classes": [], "methods": [{"name": "HelloWorld", "description": "React functional component that renders animated visual elements with configurable properties."}], "calls": ["spring", "interpolate", "useCurrentFrame", "useVideoConfig", "Logo", "Title", "Subtitle"], "search-terms": ["Remotion React component", "Animation", "TypeScript TSX React", "schema validation", "Logo component", "Subtitle component", "Title component"], "state": 2, "file_id": 2, "knowledge_revision": 23, "git_revision": "1b155e85862254c0c37899f640a7019656bd62de", "ctags": [], "hash": "006d9934bc460c136cdc7a9889c54c41", "format-version": 4, "code-base-name": "frontend_visualization_app", "filename": "frontend_visualization_app/src/HelloWorld.tsx", "revision_history": [{"23": "1b155e85862254c0c37899f640a7019656bd62de"}]}